listit/__init__.py
listit/listit.py
listit_cli-1.0.1.dist-info/METADATA
listit_cli-1.0.1.dist-info/WHEEL
listit_cli-1.0.1.dist-info/entry_points.txt
listit_cli-1.0.1.dist-info/top_level.txt
listit_cli-1.0.1.dist-info/RECORD
