Metadata-Version: 2.2
Name: listit-cli
Version: 1.0.1
Summary: A simple CLI tool to log and manage tasks
Author: GeorgeET15
Author-email: georgeemmanuelthomas@gmail.com
License: MIT
Requires-Python: >=3.6
Requires-Dist: pyfiglet>=0.8.0
Requires-Dist: inquirer>=3.0.0
Requires-Dist: rich>=12.0.0
Requires-Dist: colorama>=0.4.0
Dynamic: author
Dynamic: author-email
Dynamic: description
Dynamic: description-content-type
Dynamic: license
Dynamic: requires-dist
Dynamic: requires-python
Dynamic: summary
